complexipy_mcp/__init__.py
complexipy_mcp/server.py
complexipy_mcp-0.1.1.dist-info/METADATA
complexipy_mcp-0.1.1.dist-info/WHEEL
complexipy_mcp-0.1.1.dist-info/entry_points.txt
complexipy_mcp-0.1.1.dist-info/RECORD
