Metadata-Version: 2.4
Name: complexipy-mcp
Version: 0.1.1
Summary: A Model Context Protocol server for cognitive complexity analysis using complexipy
Project-URL: Homepage, https://github.com/Onenightcarnival/complexipy-mcp
Requires-Python: >=3.11
Requires-Dist: complexipy==5.1.0
Requires-Dist: fastmcp==2.14.2
Requires-Dist: pandas==2.3.3
Requires-Dist: pathspec==0.12.1
Requires-Dist: pydantic==2.12.5
Requires-Dist: uvicorn==0.40.0
